iws/__init__.py
iws/api/__init__.py
iws/api/client.py
iws/api/data_loader.py
iws/common/__init__.py
iws/common/exceptions.py
iws/common/types.py
iws/core/__init__.py
iws/core/climate_data.py
iws/core/stations.py
iws/core/validators.py
iws/models/__init__.py
iws/models/coordinates.py
iws/models/station.py
inmet_ws-0.2.0.dist-info/LICENSE
inmet_ws-0.2.0.dist-info/METADATA
inmet_ws-0.2.0.dist-info/WHEEL
inmet_ws-0.2.0.dist-info/RECORD
