Metadata-Version: 2.3
Name: inmet-ws
Version: 0.2.0
Summary: This package aims to make it easier to find the weather station in the INMET database closest to the desired location.
License: MIT
Keywords: weather,meteorology,inmet,geospatial
Author: Victor Benezoli
Author-email: victorbenezoli@gmail.com
Requires-Python: >=3.12,<3.14
Classifier: Development Status :: 3 - Alpha
Classifier: Intended Audience :: Developers
Classifier: License :: OSI Approved :: MIT License
Classifier: Programming Language :: Python :: 3
Classifier: Programming Language :: Python :: 3.12
Classifier: Programming Language :: Python :: 3.13
Classifier: Topic :: Scientific/Engineering :: Atmospheric Science
Requires-Dist: httpx (>=0.28.1,<0.29.0)
Requires-Dist: matplotlib (>=3.10.6,<4.0.0)
Requires-Dist: numpy (>=2.2.2,<3.0.0)
Requires-Dist: pandas (>=2.3.3,<3.0.0)
Requires-Dist: pyproj (>=3.7.0,<4.0.0)
Requires-Dist: remotezip (>=0.12.3,<0.13.0)
Requires-Dist: requests (>=2.32.3,<3.0.0)
Requires-Dist: shapely (>=2.0.6,<3.0.0)
Requires-Dist: spacy (>=3.8.7,<4.0.0)
Requires-Dist: tqdm (>=4.67.1,<5.0.0)
Project-URL: Homepage, https://github.com/victorbenezoli/inmet-stations
Project-URL: Repository, https://github.com/victorbenezoli/inmet-stations
